{
  "common": "Nasturtium",
  "botanical": "Tropaeolum majus",
  "type": "Vine",
  "lifecycle": "Annual",
  "native": "Introduced",
  "blurb": "Easy peppery-edible annual — round lily-pad leaves and spurred jewel-toned flowers that trail or climb, blooming nonstop till frost.",
  "size": "Trailing/climbing 6–10 ft (bush types ~1 ft)",
  "sun": "Full sun (part shade in extreme heat)",
  "water": "Moderate; lean soil yields more flowers",
  "spread": "Trailing/climbing annual; self-sows lightly",
  "seasons": "Round lily-pad leaves & spurred orange/red/yellow flowers, summer to frost",
  "wildlife": "Bees & hummingbirds; classic aphid trap-crop",
  "deer": "Sometimes browsed",
  "toxic": "Edible — peppery leaves, flowers & green seed pods are all edible",
  "winter": false,
  "verified": "2026-06-04",
  "shots": [
    {
      "local": "images/su-flowers-t.jpg",
      "full": "images/su-flowers.jpg",
      "url": "https://inaturalist-open-data.s3.amazonaws.com/photos/93339096/large.jpg",
      "s": "summer",
      "cap": "Summer — a spurred orange flower face-on · © indahbom (CC-BY-NC) / iNaturalist",
      "by": "indahbom",
      "lic": "CC-BY-NC",
      "link": "https://www.inaturalist.org/observations/58462350"
    },
    {
      "local": "images/su-foliage-t.jpg",
      "full": "images/su-foliage.jpg",
      "url": "https://inaturalist-open-data.s3.amazonaws.com/photos/604211395/large.jpg",
      "s": "summer",
      "cap": "Summer — the round, peltate lily-pad leaves · © Patricia Eugenia Muñoz Castro (CC-BY-NC) / iNaturalist",
      "by": "Patricia Eugenia Muñoz Castro",
      "lic": "CC-BY-NC",
      "link": "https://www.inaturalist.org/observations/332877862"
    },
    {
      "local": "images/su-close-t.jpg",
      "full": "images/su-close.jpg",
      "url": "https://inaturalist-open-data.s3.amazonaws.com/photos/487269188/large.jpeg",
      "s": "summer",
      "cap": "Summer — flowers and foliage together · © zebedeugalinha (CC-BY) / iNaturalist",
      "by": "zebedeugalinha",
      "lic": "CC-BY",
      "link": "https://www.inaturalist.org/observations/270917386"
    },
    {
      "local": "images/su-habit-t.jpg",
      "full": "images/su-habit.jpg",
      "url": "https://inaturalist-open-data.s3.amazonaws.com/photos/72667274/large.jpg",
      "s": "summer",
      "cap": "Summer — the plant trailing and scrambling · © Eduardo Nadal (CC-BY-NC) / iNaturalist",
      "by": "Eduardo Nadal",
      "lic": "CC-BY-NC",
      "link": "https://www.inaturalist.org/observations/45818707"
    }
  ]
}